[{"authors":["admin"],"categories":null,"content":"Kelsey Chalmers submitted her PhD in 2019 at the University of Sydney, and investigated the measurement of low-value procedures in Australian private health insurance claims. Prior to this, she studied and worked at the University of Queensland where she received a University Medal for her Bachelor of Science. During her PhD she was a scholarship recipient at the Capital Markets Cooperative Research Centre (in the Health Market Quality program) and a visiting Queen Elizabeth scholar at McMaster University.\n","date":-62135596800,"expirydate":-62135596800,"kind":"taxonomy","lang":"en","lastmod":-62135596800,"objectID":"2525497d367e79493fd32b198b28f040","permalink":"https://kels92.github.io/authors/admin/","publishdate":"0001-01-01T00:00:00Z","relpermalink":"/authors/admin/","section":"authors","summary":"Kelsey Chalmers submitted her PhD in 2019 at the University of Sydney, and investigated the measurement of low-value procedures in Australian private health insurance claims. Prior to this, she studied and worked at the University of Queensland where she received a University Medal for her Bachelor of Science. During her PhD she was a scholarship recipient at the Capital Markets Cooperative Research Centre (in the Health Market Quality program) and a visiting Queen Elizabeth scholar at McMaster University.","tags":null,"title":"Kelsey Chalmers","type":"authors"}]